flavio/__init__.py
flavio/_parse_errors.py
flavio/_version.py
flavio/citations.py
flavio/classes.py
flavio/config.py
flavio/functions.py
flavio/measurements.py
flavio/parameters.py
flavio/test_citations.py
flavio/test_classes.py
flavio/test_functions.py
flavio/test_measurements.py
flavio/test_parameters.py
flavio/test_parseerrors.py
flavio/util.py
flavio/data/citations.yml
flavio/data/config.yml
flavio/data/measurements.yml
flavio/data/parameters_correlated.yml
flavio/data/parameters_metadata.yml
flavio/data/parameters_uncorrelated.yml
flavio/data/test/1.yaml
flavio/data/test/2.yaml
flavio/data/test/2009.09313_digitized.npz
flavio/data/test/3.yaml
flavio/data/test/4.yaml
flavio/data/test/SPheno-2.spc.MSSM
flavio/data/test/SPheno.spc.MSSM
flavio/data/test/wcxf-flavio-example.yml
flavio/io/__init__.py
flavio/io/instanceio.py
flavio/io/test_yaml.py
flavio/io/yaml.py
flavio/math/__init__.py
flavio/math/functions.py
flavio/math/integrate.py
flavio/math/optimize.py
flavio/math/test_integrate.py
flavio/math/test_math.py
flavio/math/test_optimize.py
flavio/physics/__init__.py
flavio/physics/ckm.py
flavio/physics/common.py
flavio/physics/eft.py
flavio/physics/elements.py
flavio/physics/test_ckm.py
flavio/physics/test_common.py
flavio/physics/test_eft.py
flavio/physics/units.py
flavio/physics/bdecays/__init__.py
flavio/physics/bdecays/angular.py
flavio/physics/bdecays/bc_lifetime.py
flavio/physics/bdecays/bll.py
flavio/physics/bdecays/bllgamma.py
flavio/physics/bdecays/blnu.py
flavio/physics/bdecays/bpll.py
flavio/physics/bdecays/bpll_lfv.py
flavio/physics/bdecays/bpll_subleading.py
flavio/physics/bdecays/bplnu.py
flavio/physics/bdecays/bpnunu.py
flavio/physics/bdecays/bvgamma.py
flavio/physics/bdecays/bvlnu.py
flavio/physics/bdecays/bvnunu.py
flavio/physics/bdecays/bxgamma.py
flavio/physics/bdecays/bxll.py
flavio/physics/bdecays/bxll_qed.py
flavio/physics/bdecays/bxlnu.py
flavio/physics/bdecays/common.py
flavio/physics/bdecays/lambdablambda1520ll.py
flavio-2.6.2.dist-info/LICENSE.txt
flavio-2.6.2.dist-info/METADATA
flavio-2.6.2.dist-info/WHEEL
flavio-2.6.2.dist-info/top_level.txt
flavio-2.6.2.dist-info/RECORD
