Metadata-Version: 2.1
Name: flavio
Version: 2.6.2
Summary: A Python package for flavour physics phenomenology in the Standard Model and beyond
Home-page: https://flav-io.github.io
Author: David M. Straub
Author-email: straub@protonmail.com
License: MIT
License-File: LICENSE.txt
Requires-Dist: ckmutil >=1.2.0
Requires-Dist: numpy >=1.20.0
Requires-Dist: particle >=0.21.0
Requires-Dist: parton >=0.2.1
Requires-Dist: pyyaml
Requires-Dist: scipy
Requires-Dist: setuptools >=3.3
Requires-Dist: wilson >=2.4
Provides-Extra: plotting
Requires-Dist: matplotlib >=2.0 ; extra == 'plotting'
Provides-Extra: sampling
Requires-Dist: iminuit >=2.0 ; extra == 'sampling'
Provides-Extra: testing
Requires-Dist: nose2 ; extra == 'testing'
